hornstone/__init__.py
hornstone/alchemy.py
hornstone/archivefiles.py
hornstone/base.py
hornstone/config.py
hornstone/gitfunc.py
hornstone/path.py
hornstone/urlrepo.py
hornstone/util.py
hornstone/github/__init__.py
hornstone/github/githubdb.py
hornstone/github/populate.py
hornstone/github/repoman.py
hornstone/models/__init__.py
hornstone/models/base.py
hornstone/models/blog.py
hornstone/models/celery.py
hornstone/models/commix.py
hornstone/models/documents.py
hornstone/models/rssdata.py
hornstone/models/usergroup.py
hornstone/scrapers/__init__.py
hornstone/scrapers/base.py
hornstone/scripts/__init__.py
hornstone/scummvm/__init__.py
hornstone/scummvm/compatdevxml.py
hornstone/scummvm/runproc.py
hornstone/scummvm/scummvmdb.py
hornstone/tests/__init__.py
hornstone/tests/test_alchemy.py
hornstone/tests/test_chunks.py
hornstone/tests/test_getboolean.py
hornstone/tests/test_json_serial.py
hornstone/tmbnex/__init__.py
hornstone-0.1.23.dist-info/AUTHORS.rst
hornstone-0.1.23.dist-info/METADATA
hornstone-0.1.23.dist-info/WHEEL
hornstone-0.1.23.dist-info/top_level.txt
hornstone-0.1.23.dist-info/RECORD
