Metadata-Version: 2.1
Name: hornstone
Version: 0.1.23
Summary: A bunch of rocks
Home-page: https://github.com/umeboshi2/hornstone
Author: Joseph Rawson
Author-email: joseph.rawson.works@gmail.com
License: Public Domain
Keywords: hornstone
Platform: UNKNOWN
Classifier: Development Status :: 2 - Pre-Alpha
Classifier: Intended Audience :: Developers
Classifier: Natural Language :: English
Classifier: Programming Language :: Python :: 3
Classifier: Programming Language :: Python :: 3.5
Requires-Dist: more-itertools
Requires-Dist: SQLAlchemy
Requires-Dist: psycopg2
Requires-Dist: transaction
Requires-Dist: sqlalchemy-utils
Requires-Dist: robobrowser
Requires-Dist: requests
Requires-Dist: beautifulsoup4
Requires-Dist: lxml
Requires-Dist: rarfile
Requires-Dist: unipath
Requires-Dist: PyGithub
Requires-Dist: gitpython
Requires-Dist: passlib
